Workbook

Sheet Допущения
A1: ДОПУЩЕНИЯ И ВХОДНЫЕ ДАННЫЕ
A2: Синий текст = вводимые данные (можно изменять). Чёрный = расчётные.
A3: Параметр | B3: Значение | C3: Ед. изм. | D3: Комментарий
A4: ── ЦЕНООБРАЗОВАНИЕ ──
A5: Цена устройства (ASP) | B5: 8500 | C5: ₽ | D5: Целевой диапазон 7 000–10 000 ₽ по данным UX-теста
A6: COGS на единицу | B6: 4200 | C6: ₽ | D6: ~50% ASP: компоненты + сборка + упаковка
A7: Гарантийный резерв, % COGS | B7: 0.05 | C7: % | D7: 5% от COGS на гарантийные замены
A8: ── ВОРОНКА ПРОДАЖ ──
A9: Контактов в М1 (outreach) | B9: 80 | C9: шт | D9: Стартовый охват через Telegram + маркетплейсы
A10: Прирост контактов в месяц | B10: 40 | C10: шт | D10: Органический рост + реферал
A11: Reply rate | B11: 0.3 | C11: % | D11: Доля ответивших на первичный контакт
A12: Demo-to-contact rate | B12: 0.5 | C12: % | D12: Доля выходящих на демо от ответивших
A13: Конверсия в покупку | B13: 0.2 | C13: % | D13: Доля купивших от прошедших демо
A14: Retention: повторный заказ | B14: 0.1 | C14: % | D14: Доп. аксессуары / чехол / замена через 18 мес.
A15: ── ОПЕРАЦИОННЫЕ ЗАТРАТЫ ──
A16: Маркетинг, в месяц | B16: 50000 | C16: ₽ | D16: Реклама: Telegram Ads, обзоры блогеров, Wildberries
A17: Разработка / прошивка, в мес | B17: 80000 | C17: ₽ | D17: 1 fullstack-разработчик (частичная занятость)
A18: Операционные (логистика, КС) | B18: 30000 | C18: ₽ | D18: Склад, доставка, поддержка клиентов
A19: ── СЦЕНАРИИ (Анализ чувствительности) ──
A20: Reply rate — консервативный | B20: 0.2 | C20: % | D20: Холодный outreach без прогрева
A21: Reply rate — оптимистичный | B21: 0.4 | C21: % | D21: Тёплые лиды + рекомендации
A22: Конверсия — консервативная | B22: 0.1 | C22: % | D22: Высокий барьер: цена, доверие к новому бренду
A23: Конверсия — оптимистичная | B23: 0.3 | C23: % | D23: После видео-обзора + промо-скидки -10%
A24: Контакты М1 — консервативно | B24: 50 | C24: шт | D24: Медленный старт
A25: Контакты М1 — оптимистично | B25: 120 | C25: шт | D25: Агрессивный outreach

Sheet Финмодель (12 мес)
A1: ФИНАНСОВАЯ МОДЕЛЬ — Портативный Wi-Fi SSD (горизонт 12 месяцев)
A2: Базовый сценарий · Все суммы в рублях · Синий текст = ввод · Чёрный = расчёт
A3: Показатель | B3: М1 | C3: М2 | D3: М3 | E3: М4 | F3: М5 | G3: М6 | H3: М7 | I3: М8 | J3: М9 | K3: М10 | L3: М11 | M3: М12 | N3: ИТОГО / ГОД
A4: 🔸 БЛОК 1. ВОРОНКА ПРОДАЖ
A5: Контактов (outreach) | B5: =Допущения!$B$9+Допущения!$B$10*0 -> 80 | C5: =Допущения!$B$9+Допущения!$B$10*1 -> 120 | D5: =Допущения!$B$9+Допущения!$B$10*2 -> 160 | E5: =Допущения!$B$9+Допущения!$B$10*3 -> 200 | F5: =Допущения!$B$9+Допущения!$B$10*4 -> 240 | G5: =Допущения!$B$9+Допущения!$B$10*5 -> 280 | H5: =Допущения!$B$9+Допущения!$B$10*6 -> 320 | I5: =Допущения!$B$9+Допущения!$B$10*7 -> 360 | J5: =Допущения!$B$9+Допущения!$B$10*8 -> 400 | K5: =Допущения!$B$9+Допущения!$B$10*9 -> 440 | L5: =Допущения!$B$9+Допущения!$B$10*10 -> 480 | M5: =Допущения!$B$9+Допущения!$B$10*11 -> 520 | N5: =SUM(B5:M5) -> 3600
A6: Ответили (reply rate) | B6: =ROUND(B5*Допущения!$B$11,0) -> 24 | C6: =ROUND(C5*Допущения!$B$11,0) -> 36 | D6: =ROUND(D5*Допущения!$B$11,0) -> 48 | E6: =ROUND(E5*Допущения!$B$11,0) -> 60 | F6: =ROUND(F5*Допущения!$B$11,0) -> 72 | G6: =ROUND(G5*Допущения!$B$11,0) -> 84 | H6: =ROUND(H5*Допущения!$B$11,0) -> 96 | I6: =ROUND(I5*Допущения!$B$11,0) -> 108 | ... M6: =ROUND(M5*Допущения!$B$11,0) -> 156 | N6: =SUM(B6:M6) -> 1080
A7: Демо / созвоны | B7: =ROUND(B6*Допущения!$B$12,0) -> 12 | C7: =ROUND(C6*Допущения!$B$12,0) -> 18 | D7: =ROUND(D6*Допущения!$B$12,0) -> 24 | E7: =ROUND(E6*Допущения!$B$12,0) -> 30 | F7: =ROUND(F6*Допущения!$B$12,0) -> 36 | G7: =ROUND(G6*Допущения!$B$12,0) -> 42 | H7: =ROUND(H6*Допущения!$B$12,0) -> 48 | I7: =ROUND(I6*Допущения!$B$12,0) -> 54 | ... M7: =ROUND(M6*Допущения!$B$12,0) -> 78 | N7: =SUM(B7:M7) -> 540
A8: Продажи (ед.) | B8: =ROUND(B7*Допущения!$B$13,0) -> 2 | C8: =ROUND(C7*Допущения!$B$13,0) -> 4 | D8: =ROUND(D7*Допущения!$B$13,0) -> 5 | E8: =ROUND(E7*Допущения!$B$13,0) -> 6 | F8: =ROUND(F7*Допущения!$B$13,0) -> 7 | G8: =ROUND(G7*Допущения!$B$13,0) -> 8 | H8: =ROUND(H7*Допущения!$B$13,0) -> 10 | I8: =ROUND(I7*Допущения!$B$13,0) -> 11 | ... M8: =ROUND(M7*Допущения!$B$13,0) -> 16 | N8: =SUM(B8:M8) -> 108
A9: Нарастающим итогом, ед. | B9: =B8 -> 2 | C9: =B9+C8 -> 6 | D9: =C9+D8 -> 11 | E9: =D9+E8 -> 17 | F9: =E9+F8 -> 24 | G9: =F9+G8 -> 32 | H9: =G9+H8 -> 42 | I9: =H9+I8 -> 53 | J9: =I9+J8 -> 65 | ... M9: =L9+M8 -> 108 | N9: =M9 -> 108
A11: 🔸 БЛОК 2. ВЫРУЧКА
A12: Цена ед. (ASP), ₽ | B12: =Допущения!$B$5 -> 8500 | C12: =Допущения!$B$5 -> 8500 | D12: =Допущения!$B$5 -> 8500 | E12: =Допущения!$B$5 -> 8500 | F12: =Допущения!$B$5 -> 8500 | G12: =Допущения!$B$5 -> 8500 | H12: =Допущения!$B$5 -> 8500 | I12: =Допущения!$B$5 -> 8500 | ... N12: =Допущения!$B$5 -> 8500
A13: Выручка, ₽ | B13: =B8*B12 -> 17000 | C13: =C8*C12 -> 34000 | D13: =D8*D12 -> 42500 | E13: =E8*E12 -> 51000 | F13: =F8*F12 -> 59500 | G13: =G8*G12 -> 68000 | H13: =H8*H12 -> 85000 | I13: =I8*I12 -> 93500 | ... M13: =M8*M12 -> 136000 | N13: =SUM(B13:M13) -> 918000
A14: Нарастающим итогом, ₽ | B14: =B13 -> 17000 | C14: =B14+C13 -> 51000 | D14: =C14+D13 -> 93500 | E14: =D14+E13 -> 144500 | F14: =E14+F13 -> 204000 | G14: =F14+G13 -> 272000 | H14: =G14+H13 -> 357000 | I14: =H14+I13 -> 450500 | J14: =I14+J13 -> 552500 | ... M14: =L14+M13 -> 918000 | N14: =M14 -> 918000
A16: 🔸 БЛОК 3. COGS И ВАЛОВАЯ ПРИБЫЛЬ
A17: COGS на ед., ₽ | B17: =Допущения!$B$6 -> 4200 | C17: =Допущения!$B$6 -> 4200 | D17: =Допущения!$B$6 -> 4200 | E17: =Допущения!$B$6 -> 4200 | F17: =Допущения!$B$6 -> 4200 | G17: =Допущения!$B$6 -> 4200 | H17: =Допущения!$B$6 -> 4200 | I17: =Допущения!$B$6 -> 4200 | ... N17: =Допущения!$B$6 -> 4200
A18: Гарантийный резерв, ₽ | B18: =B8*Допущения!$B$6*Допущения!$B$7 -> 420 | C18: =C8*Допущения!$B$6*Допущения!$B$7 -> 840 | D18: =D8*Допущения!$B$6*Допущения!$B$7 -> 1050 | E18: =E8*Допущения!$B$6*Допущения!$B$7 -> 1260 | F18: =F8*Допущения!$B$6*Допущения!$B$7 -> 1470 | G18: =G8*Допущения!$B$6*Допущения!$B$7 -> 1680 | H18: =H8*Допущения!$B$6*Допущения!$B$7 -> 2100 | I18: =I8*Допущения!$B$6*Допущения!$B$7 -> 2310 | ... M18: =M8*Допущения!$B$6*Допущения!$B$7 -> 3360 | N18: =SUM(B18:M18) -> 22680
A19: Итого COGS, ₽ | B19: =B8*B17+B18 -> 8820 | C19: =C8*C17+C18 -> 17640 | D19: =D8*D17+D18 -> 22050 | E19: =E8*E17+E18 -> 26460 | F19: =F8*F17+F18 -> 30870 | G19: =G8*G17+G18 -> 35280 | H19: =H8*H17+H18 -> 44100 | I19: =I8*I17+I18 -> 48510 | ... M19: =M8*M17+M18 -> 70560 | N19: =SUM(B19:M19) -> 476280
A20: Валовая прибыль, ₽ | B20: =B13-B19 -> 8180 | C20: =C13-C19 -> 16360 | D20: =D13-D19 -> 20450 | E20: =E13-E19 -> 24540 | F20: =F13-F19 -> 28630 | G20: =G13-G19 -> 32720 | H20: =H13-H19 -> 40900 | I20: =I13-I19 -> 44990 | ... M20: =M13-M19 -> 65440 | N20: =SUM(B20:M20) -> 441720
A21: Валовая маржа, % | B21: =IF(B13=0,0,B20/B13) -> 0.48117647 | C21: =IF(C13=0,0,C20/C13) -> 0.48117647 | D21: =IF(D13=0,0,D20/D13) -> 0.48117647 | E21: =IF(E13=0,0,E20/E13) -> 0.48117647 | F21: =IF(F13=0,0,F20/F13) -> 0.48117647 | G21: =IF(G13=0,0,G20/G13) -> 0.48117647 | H21: =IF(H13=0,0,H20/H13) -> 0.48117647 | I21: =IF(I13=0,0,I20/I13) -> 0.48117647 | ... M21: =IF(M13=0,0,M20/M13) -> 0.48117647 | N21: =IF(SUM(B13:M13)=0,0,SUM(B20:M20)/SUM(B13:M13)) -> 0.48117647
A23: 🔸 БЛОК 4. ОПЕРАЦИОННЫЕ ЗАТРАТЫ (OPEX)
A24: Маркетинг, ₽ | B24: =Допущения!$B$16 -> 50000 | C24: =Допущения!$B$16 -> 50000 | D24: =Допущения!$B$16 -> 50000 | E24: =Допущения!$B$16 -> 50000 | F24: =Допущения!$B$16 -> 50000 | G24: =Допущения!$B$16 -> 50000 | H24: =Допущения!$B$16 -> 50000 | I24: =Допущения!$B$16 -> 50000 | ... M24: =Допущения!$B$16 -> 50000 | N24: =SUM(B24:M24) -> 600000
A25: Разработка, ₽ | B25: =Допущения!$B$17 -> 80000 | C25: =Допущения!$B$17 -> 80000 | D25: =Допущения!$B$17 -> 80000 | E25: =Допущения!$B$17 -> 80000 | F25: =Допущения!$B$17 -> 80000 | G25: =Допущения!$B$17 -> 80000 | H25: =Допущения!$B$17 -> 80000 | I25: =Допущения!$B$17 -> 80000 | ... M25: =Допущения!$B$17 -> 80000 | N25: =SUM(B25:M25) -> 960000
A26: Операционные, ₽ | B26: =Допущения!$B$18 -> 30000 | C26: =Допущения!$B$18 -> 30000 | D26: =Допущения!$B$18 -> 30000 | E26: =Допущения!$B$18 -> 30000 | F26: =Допущения!$B$18 -> 30000 | G26: =Допущения!$B$18 -> 30000 | H26: =Допущения!$B$18 -> 30000 | I26: =Допущения!$B$18 -> 30000 | ... M26: =Допущения!$B$18 -> 30000 | N26: =SUM(B26:M26) -> 360000
A27: Итого OPEX, ₽ | B27: =B24+B25+B26 -> 160000 | C27: =C24+C25+C26 -> 160000 | D27: =D24+D25+D26 -> 160000 | E27: =E24+E25+E26 -> 160000 | F27: =F24+F25+F26 -> 160000 | G27: =G24+G25+G26 -> 160000 | H27: =H24+H25+H26 -> 160000 | I27: =I24+I25+I26 -> 160000 | ... M27: =M24+M25+M26 -> 160000 | N27: =SUM(B27:M27) -> 1920000
A29: 🔸 БЛОК 5. ИТОГИ
A30: EBITDA (операц. прибыль), ₽ | B30: =B20-B27 -> -151820 | C30: =C20-C27 -> -143640 | D30: =D20-D27 -> -139550 | E30: =E20-E27 -> -135460 | F30: =F20-F27 -> -131370 | G30: =G20-G27 -> -127280 | H30: =H20-H27 -> -119100 | I30: =I20-I27 -> -115010 | ... M30: =M20-M27 -> -94560 | N30: =SUM(B30:M30) -> -1478280
A31: EBITDA маржа, % | B31: =IF(B13=0,0,B30/B13) -> -8.9305882 | C31: =IF(C13=0,0,C30/C13) -> -4.2247059 | D31: =IF(D13=0,0,D30/D13) -> -3.2835294 | E31: =IF(E13=0,0,E30/E13) -> -2.6560784 | F31: =IF(F13=0,0,F30/F13) -> -2.2078992 | G31: =IF(G13=0,0,G30/G13) -> -1.8717647 | H31: =IF(H13=0,0,H30/H13) -> -1.4011765 | I31: =IF(I13=0,0,I30/I13) -> -1.2300535 | ... N31: =IF(N13=0,0,N30/N13) -> -1.6103268
A32: Накопленный денежный поток, ₽ | B32: =B30 -> -151820 | C32: =B32+C30 -> -295460 | D32: =C32+D30 -> -435010 | E32: =D32+E30 -> -570470 | F32: =E32+F30 -> -701840 | G32: =F32+G30 -> -829120 | H32: =G32+H30 -> -948220 | I32: =H32+I30 -> -1063230 | J32: =I32+J30 -> -1174150 | ... M32: =L32+M30 -> -1478280 | N32: =M32 -> -1478280

Sheet Анализ чувствительности
A1: АНАЛИЗ ЧУВСТВИТЕЛЬНОСТИ — 3 СЦЕНАРИЯ (годовой горизонт)
A2: Варьируемые параметры: Reply Rate, Конверсия в покупку, Контакты М1. Прочие = базовые (лист Допущения).
A3: Параметр / Метрика | B3: Консервативный | C3: Базовый | D3: Оптимистичный | E3: Ед. изм. | F3: Комментарий
A4: ── ВХОДНЫЕ ПАРАМЕТРЫ ──
A5: Reply Rate | B5: =Допущения!$B$20 -> 0.2 | C5: =Допущения!$B$11 -> 0.3 | D5: =Допущения!$B$21 -> 0.4 | E5: % | F5: Доля ответивших на outreach
A6: Конверсия в покупку | B6: =Допущения!$B$22 -> 0.1 | C6: =Допущения!$B$13 -> 0.2 | D6: =Допущения!$B$23 -> 0.3 | E6: % | F6: Доля купивших от прошедших демо
A7: Контакты в М1 | B7: =Допущения!$B$24 -> 50 | C7: =Допущения!$B$9 -> 80 | D7: =Допущения!$B$25 -> 120 | E7: шт | F7: Стартовый охват
A8: Прирост контактов/мес | B8: =Допущения!$B$10 -> 40 | C8: =Допущения!$B$10 -> 40 | D8: =Допущения!$B$10 -> 40 | E8: шт | F8: Одинаковый во всех сценариях
A9: Demo rate | B9: =Допущения!$B$12 -> 0.5 | C9: =Допущения!$B$12 -> 0.5 | D9: =Допущения!$B$12 -> 0.5 | E9: % | F9: Одинаковый во всех сценариях
A10: Цена устройства (ASP) | B10: =Допущения!$B$5 -> 8500 | C10: =Допущения!$B$5 -> 8500 | D10: =Допущения!$B$5 -> 8500 | E10: ₽ | F10: Одинаковая во всех сценариях
A11: ── РАСЧЁТНЫЕ МЕТРИКИ (12 мес) ──
A12: Контактов всего (год) | B12: =12*Допущения!$B$24+Допущения!$B$10*66 -> 3240 | C12: =12*Допущения!$B$9+Допущения!$B$10*66 -> 3600 | D12: =12*Допущения!$B$25+Допущения!$B$10*66 -> 4080 | E12: шт | F12: Суммарный outreach за 12 мес.
A13: Продаж всего (год), ед. | B13: =ROUND(ROUND(ROUND((12*Допущения!$B$24+Допущения!$B$10*66)*Допущения!$B$20,0)*Допущения!$B$12,0)*Допущения!$B$22,0) -> 32 | C13: =ROUND(ROUND(ROUND((12*Допущения!$B$9+Допущения!$B$10*66)*Допущения!$B$11,0)*Допущения!$B$12,0)*Допущения!$B$13,0) -> 108 | D13: =ROUND(ROUND(ROUND((12*Допущения!$B$25+Допущения!$B$10*66)*Допущения!$B$21,0)*Допущения!$B$12,0)*Допущения!$B$23,0) -> 245 | E13: шт | F13: Суммарные продажи устройств
A14: Выручка (год), ₽ | B14: =ROUND(ROUND(ROUND(ROUND((12*Допущения!$B$24+Допущения!$B$10*66)*Допущения!$B$20,0)*Допущения!$B$12,0)*Допущения!$B$22,0)*Допущения!$B$5,0) -> 272000 | C14: =ROUND(ROUND(ROUND(ROUND((12*Допущения!$B$9+Допущения!$B$10*66)*Допущения!$B$11,0)*Допущения!$B$12,0)*Допущения!$B$13,0)*Допущения!$B$5,0) -> 918000 | D14: =ROUND(ROUND(ROUND(ROUND((12*Допущения!$B$25+Допущения!$B$10*66)*Допущения!$B$21,0)*Допущения!$B$12,0)*Допущения!$B$23,0)*Допущения!$B$5,0) -> 2082500 | E14: ₽ | F14: Продажи × ASP
A15: Валовая прибыль (год), ₽ | B15: =ROUND(ROUND(ROUND(ROUND((12*Допущения!$B$24+Допущения!$B$10*66)*Допущения!$B$20,0)*Допущения!$B$12,0)*Допущения!$B$22,0)*Допущения!$B$5,0)-ROUND(ROUND(ROUND(ROUND((12*Допущения!$B$24+Допущения!$B$10*66)*Допущения!$B$20,0)*Допущения!$B$12,0)*Допущения!$B$22,0)*Допущения!$B$6,0) -> 137600 | C15: =ROUND(ROUND(ROUND(ROUND((12*Допущения!$B$9+Допущения!$B$10*66)*Допущения!$B$11,0)*Допущения!$B$12,0)*Допущения!$B$13,0)*Допущения!$B$5,0)-ROUND(ROUND(ROUND(ROUND((12*Допущения!$B$9+Допущения!$B$10*66)*Допущения!$B$11,0)*Допущения!$B$12,0)*Допущения!$B$13,0)*Допущения!$B$6,0) -> 464400 | D15: =ROUND(ROUND(ROUND(ROUND((12*Допущения!$B$25+Допущения!$B$10*66)*Допущения!$B$21,0)*Допущения!$B$12,0)*Допущения!$B$23,0)*Допущения!$B$5,0)-ROUND(ROUND(ROUND(ROUND((12*Допущения!$B$25+Допущения!$B$10*66)*Допущения!$B$21,0)*Допущения!$B$12,0)*Допущения!$B$23,0)*Допущения!$B$6,0) -> 1053500 | E15: ₽ | F15: Выручка − COGS
A16: EBITDA (год), ₽ | B16: =ROUND(ROUND(ROUND(ROUND((12*Допущения!$B$24+Допущения!$B$10*66)*Допущения!$B$20,0)*Допущения!$B$12,0)*Допущения!$B$22,0)*Допущения!$B$5,0)-ROUND(ROUND(ROUND(ROUND((12*Допущения!$B$24+Допущения!$B$10*66)*Допущения!$B$20,0)*Допущения!$B$12,0)*Допущения!$B$22,0)*Допущения!$B$6,0)-(Допущения!$B$16+Допущения!$B$17+Допущения!$B$18)*12 -> -1782400 | C16: =ROUND(ROUND(ROUND(ROUND((12*Допущения!$B$9+Допущения!$B$10*66)*Допущения!$B$11,0)*Допущения!$B$12,0)*Допущения!$B$13,0)*Допущения!$B$5,0)-ROUND(ROUND(ROUND(ROUND((12*Допущения!$B$9+Допущения!$B$10*66)*Допущения!$B$11,0)*Допущения!$B$12,0)*Допущения!$B$13,0)*Допущения!$B$6,0)-(Допущения!$B$16+Допущения!$B$17+Допущения!$B$18)*12 -> -1455600 | D16: =ROUND(ROUND(ROUND(ROUND((12*Допущения!$B$25+Допущения!$B$10*66)*Допущения!$B$21,0)*Допущения!$B$12,0)*Допущения!$B$23,0)*Допущения!$B$5,0)-ROUND(ROUND(ROUND(ROUND((12*Допущения!$B$25+Допущения!$B$10*66)*Допущения!$B$21,0)*Допущения!$B$12,0)*Допущения!$B$23,0)*Допущения!$B$6,0)-(Допущения!$B$16+Допущения!$B$17+Допущения!$B$18)*12 -> -866500 | E16: ₽ | F16: Валовая прибыль − OPEX
A17: EBITDA маржа, % | B17: =IF(ROUND(ROUND(ROUND(ROUND((12*Допущения!$B$24+Допущения!$B$10*66)*Допущения!$B$20,0)*Допущения!$B$12,0)*Допущения!$B$22,0)*Допущения!$B$5,0)=0,0,(ROUND(ROUND(ROUND(ROUND((12*Допущения!$B$24+Допущения!$B$10*66)*Допущения!$B$20,0)*Допущения!$B$12,0)*Допущения!$B$22,0)*Допущения!$B$5,0)-ROUND(ROUND(ROUND(ROUND((12*Допущения!$B$24+Допущения!$B$10*66)*Допущения!$B$20,0)*Допущения!$B$12,0)*Допущения!$B$22,0)*Допущения!$B$6,0)-(Допущения!$B$16+Допущения!$B$17+Допущения!$B$18)*12)/(ROUND(ROUND(ROUND(ROUND((12*Допущения!$B$24+Допущения!$B$10*66)*Допущения!$B$20,0)*Допущения!$B$12,0)*Допущения!$B$22,0)*Допущения!$B$5,0))) -> -6.5529412 | C17: =IF(ROUND(ROUND(ROUND(ROUND((12*Допущения!$B$9+Допущения!$B$10*66)*Допущения!$B$11,0)*Допущения!$B$12,0)*Допущения!$B$13,0)*Допущения!$B$5,0)=0,0,(ROUND(ROUND(ROUND(ROUND((12*Допущения!$B$9+Допущения!$B$10*66)*Допущения!$B$11,0)*Допущения!$B$12,0)*Допущения!$B$13,0)*Допущения!$B$5,0)-ROUND(ROUND(ROUND(ROUND((12*Допущения!$B$9+Допущения!$B$10*66)*Допущения!$B$11,0)*Допущения!$B$12,0)*Допущения!$B$13,0)*Допущения!$B$6,0)-(Допущения!$B$16+Допущения!$B$17+Допущения!$B$18)*12)/(ROUND(ROUND(ROUND(ROUND((12*Допущения!$B$9+Допущения!$B$10*66)*Допущения!$B$11,0)*Допущения!$B$12,0)*Допущения!$B$13,0)*Допущения!$B$5,0))) -> -1.5856209 | D17: =IF(ROUND(ROUND(ROUND(ROUND((12*Допущения!$B$25+Допущения!$B$10*66)*Допущения!$B$21,0)*Допущения!$B$12,0)*Допущения!$B$23,0)*Допущения!$B$5,0)=0,0,(ROUND(ROUND(ROUND(ROUND((12*Допущения!$B$25+Допущения!$B$10*66)*Допущения!$B$21,0)*Допущения!$B$12,0)*Допущения!$B$23,0)*Допущения!$B$5,0)-ROUND(ROUND(ROUND(ROUND((12*Допущения!$B$25+Допущения!$B$10*66)*Допущения!$B$21,0)*Допущения!$B$12,0)*Допущения!$B$23,0)*Допущения!$B$6,0)-(Допущения!$B$16+Допущения!$B$17+Допущения!$B$18)*12)/(ROUND(ROUND(ROUND(ROUND((12*Допущения!$B$25+Допущения!$B$10*66)*Допущения!$B$21,0)*Допущения!$B$12,0)*Допущения!$B$23,0)*Допущения!$B$5,0))) -> -0.41608643 | E17: % | F17: EBITDA / Выручка
A19: Источники: IDC External Storage Tracker Q4 2024; Mediascope РФ 2024; UX-тест (март 2026, n=7); анализ Ozon/Wildberries март 2026; собственные расчёты.
